malayalam_hate_detector/__init__.py
malayalam_hate_detector/detector.py
malayalam_hate_detector-1.0.1.dist-info/METADATA
malayalam_hate_detector-1.0.1.dist-info/WHEEL
malayalam_hate_detector-1.0.1.dist-info/top_level.txt
malayalam_hate_detector-1.0.1.dist-info/RECORD
