Metadata-Version: 2.4
Name: malayalam-hate-detector
Version: 1.0.1
Summary: Advanced Malayalam Hate Speech Detection
Author: Your Name
Author-email: your.email@example.com
Classifier: Development Status :: 4 - Beta
Classifier: Intended Audience :: Developers
Classifier: License :: OSI Approved :: MIT License
Classifier: Operating System :: OS Independent
Classifier: Programming Language :: Python :: 3
Requires-Python: >=3.7
Requires-Dist: speechrecognition>=3.8.1
Requires-Dist: transformers>=4.20.0
Requires-Dist: torch>=1.12.0
Requires-Dist: pyaudio>=0.2.11
Dynamic: author
Dynamic: author-email
Dynamic: classifier
Dynamic: description
Dynamic: description-content-type
Dynamic: requires-dist
Dynamic: requires-python
Dynamic: summary
